Metadata-Version: 1.1
Name: django-any-response-redirect-middleware
Version: 1.0
Summary: A subclass of Django's RedirectFallbackMiddleware that will catch any response code, not just 404s.
Home-page: https://github.com/ryanbagwell/django-any-response-redirect-middleware/
Author: Ryan Bagwell
Author-email: ryan@ryanbagwell.com
License: UNKNOWN
Platform: UNKNOWN
Classifier: Environment :: Web Environment
Classifier: Framework :: Django
Classifier: Intended Audience :: Developers
Classifier: Programming Language :: Python
Classifier: Topic :: Internet :: WWW/HTTP
